helpers/__init__.py
helpers/utils.py
mstock_tradingapi_b-1.0.5.dist-info/licenses/LICENSE
tradingapi_b/__config__.py
tradingapi_b/__init__.py
tradingapi_b/exceptions.py
tradingapi_b/mconnect.py
tradingapi_b/mticker.py
mstock_tradingapi_b-1.0.5.dist-info/METADATA
mstock_tradingapi_b-1.0.5.dist-info/WHEEL
mstock_tradingapi_b-1.0.5.dist-info/top_level.txt
mstock_tradingapi_b-1.0.5.dist-info/RECORD
