Metadata-Version: 2.4
Name: mStock-TradingApi-B
Version: 1.0.5
Summary: A Python SDK for Connecting to mStock Trading API and Streaming API
Home-page: https://github.com/MiraeAsset-mStock/pytradingapi-typeB
Author: Mirae Asset Capital Markets (India) Private Limited
Classifier: Programming Language :: Python :: 3
Classifier: License :: OSI Approved :: MIT License
Classifier: Operating System :: OS Independent
Classifier: Development Status :: 5 - Production/Stable
Classifier: Intended Audience :: Developers
Classifier: Intended Audience :: Financial and Insurance Industry
Classifier: Natural Language :: English
Classifier: Programming Language :: Python :: 3.5
Classifier: Programming Language :: Python :: 3.6
Classifier: Programming Language :: Python :: 3.7
Classifier: Topic :: Office/Business :: Financial :: Investment
Classifier: Topic :: Software Development :: Libraries :: Python Modules
Classifier: Topic :: Software Development :: Libraries
Requires-Python: >=3.11
License-File: LICENSE
Requires-Dist: autobahn
Requires-Dist: requests
Requires-Dist: responses
Requires-Dist: pytest
Requires-Dist: setuptools
Requires-Dist: twisted
Dynamic: author
Dynamic: classifier
Dynamic: description
Dynamic: description-content-type
Dynamic: home-page
Dynamic: license-file
Dynamic: requires-dist
Dynamic: requires-python
Dynamic: summary
